README.txt
setup.cfg
setup.py
SchemaBot.egg-info/PKG-INFO
SchemaBot.egg-info/SOURCES.txt
SchemaBot.egg-info/dependency_links.txt
SchemaBot.egg-info/entry_points.txt
SchemaBot.egg-info/not-zip-safe
SchemaBot.egg-info/requires.txt
SchemaBot.egg-info/top_level.txt
docs/schemabot-with-pylons.txt
schemabot/__init__.py
tests/test_schemabot.py