Metadata-Version: 1.0
Name: SchemaBot
Version: 0.0.5
Summary: Database schema version control library for SQLAlchemy
Home-page: UNKNOWN
Author: Chris Miles
Author-email: miles.chris@gmail.com
License: MIT
Platform: UNKNOWN
